Workbook

Sheet Übersicht
A1: Adventskalender 2026 – Übersicht
A2: Heute: | B2: =TODAY() -> 46319
A3: Verkauf live (29.10.) in Tagen: | B3: =DATE(2026,10,29)-TODAY() -> 5
A4: Early Bird endet (15.11.) in Tagen: | B4: =DATE(2026,11,15)-TODAY() -> 22
A5: Kalender startet (1.12.) in Tagen: | B5: =DATE(2026,12,1)-TODAY() -> 38
A6: Aufgaben gesamt / erledigt / offen: | B6: =COUNTA(Gesamtplan!C2:C157) -> 156 | C6: =COUNTIF(Gesamtplan!H2:H157,"erledigt") -> 14 | D6: =B6-C6 -> 142
A7: Überfällig: | B7: =COUNTIF(Gesamtplan!M2:M157,"ÜBERFÄLLIG") -> 0
A8: Bald fällig (2 Tage): | B8: =COUNTIF(Gesamtplan!M2:M157,"bald fällig") -> 11
A10: Bereich | B10: Aufgaben | C10: erledigt | D10: offen | E10: überfällig
A11: Orga & Budget | B11: =COUNTIF(Gesamtplan!$B$2:$B$157,A11) -> 11 | C11: =COUNTIFS(Gesamtplan!$B$2:$B$157,A11,Gesamtplan!$H$2:$H$157,"erledigt") -> 3 | D11: =B11-C11 -> 8 | E11: =COUNTIFS(Gesamtplan!$B$2:$B$157,A11,Gesamtplan!$M$2:$M$157,"ÜBERFÄLLIG") -> 0
A12: Produktion | B12: =COUNTIF(Gesamtplan!$B$2:$B$157,A12) -> 25 | C12: =COUNTIFS(Gesamtplan!$B$2:$B$157,A12,Gesamtplan!$H$2:$H$157,"erledigt") -> 2 | D12: =B12-C12 -> 23 | E12: =COUNTIFS(Gesamtplan!$B$2:$B$157,A12,Gesamtplan!$M$2:$M$157,"ÜBERFÄLLIG") -> 0
A13: Shop & Technik | B13: =COUNTIF(Gesamtplan!$B$2:$B$157,A13) -> 18 | C13: =COUNTIFS(Gesamtplan!$B$2:$B$157,A13,Gesamtplan!$H$2:$H$157,"erledigt") -> 0 | D13: =B13-C13 -> 18 | E13: =COUNTIFS(Gesamtplan!$B$2:$B$157,A13,Gesamtplan!$M$2:$M$157,"ÜBERFÄLLIG") -> 0
A14: Warteliste & Mail | B14: =COUNTIF(Gesamtplan!$B$2:$B$157,A14) -> 20 | C14: =COUNTIFS(Gesamtplan!$B$2:$B$157,A14,Gesamtplan!$H$2:$H$157,"erledigt") -> 4 | D14: =B14-C14 -> 16 | E14: =COUNTIFS(Gesamtplan!$B$2:$B$157,A14,Gesamtplan!$M$2:$M$157,"ÜBERFÄLLIG") -> 0
A15: Werbung organisch | B15: =COUNTIF(Gesamtplan!$B$2:$B$157,A15) -> 22 | C15: =COUNTIFS(Gesamtplan!$B$2:$B$157,A15,Gesamtplan!$H$2:$H$157,"erledigt") -> 0 | D15: =B15-C15 -> 22 | E15: =COUNTIFS(Gesamtplan!$B$2:$B$157,A15,Gesamtplan!$M$2:$M$157,"ÜBERFÄLLIG") -> 0
A16: Werbung bezahlt | B16: =COUNTIF(Gesamtplan!$B$2:$B$157,A16) -> 13 | C16: =COUNTIFS(Gesamtplan!$B$2:$B$157,A16,Gesamtplan!$H$2:$H$157,"erledigt") -> 0 | D16: =B16-C16 -> 13 | E16: =COUNTIFS(Gesamtplan!$B$2:$B$157,A16,Gesamtplan!$M$2:$M$157,"ÜBERFÄLLIG") -> 0
A17: Gewinnspiel | B17: =COUNTIF(Gesamtplan!$B$2:$B$157,A17) -> 19 | C17: =COUNTIFS(Gesamtplan!$B$2:$B$157,A17,Gesamtplan!$H$2:$H$157,"erledigt") -> 3 | D17: =B17-C17 -> 16 | E17: =COUNTIFS(Gesamtplan!$B$2:$B$157,A17,Gesamtplan!$M$2:$M$157,"ÜBERFÄLLIG") -> 0
A18: Recht & Rechte | B18: =COUNTIF(Gesamtplan!$B$2:$B$157,A18) -> 9 | C18: =COUNTIFS(Gesamtplan!$B$2:$B$157,A18,Gesamtplan!$H$2:$H$157,"erledigt") -> 1 | D18: =B18-C18 -> 8 | E18: =COUNTIFS(Gesamtplan!$B$2:$B$157,A18,Gesamtplan!$M$2:$M$157,"ÜBERFÄLLIG") -> 0
A19: Korea & USA | B19: =COUNTIF(Gesamtplan!$B$2:$B$157,A19) -> 12 | C19: =COUNTIFS(Gesamtplan!$B$2:$B$157,A19,Gesamtplan!$H$2:$H$157,"erledigt") -> 1 | D19: =B19-C19 -> 11 | E19: =COUNTIFS(Gesamtplan!$B$2:$B$157,A19,Gesamtplan!$M$2:$M$157,"ÜBERFÄLLIG") -> 0
A20: Betrieb Dezember | B20: =COUNTIF(Gesamtplan!$B$2:$B$157,A20) -> 7 | C20: =COUNTIFS(Gesamtplan!$B$2:$B$157,A20,Gesamtplan!$H$2:$H$157,"erledigt") -> 0 | D20: =B20-C20 -> 7 | E20: =COUNTIFS(Gesamtplan!$B$2:$B$157,A20,Gesamtplan!$M$2:$M$157,"ÜBERFÄLLIG") -> 0
A21: Summe | B21: =SUM(B11:B20) -> 156 | C21: =SUM(C11:C20) -> 14 | D21: =SUM(D11:D20) -> 142 | E21: =SUM(E11:E20) -> 0
A23: So benutzt du die Tabelle
A24: Blatt „Gesamtplan“: alle Aufgaben nach Frist sortiert. Spalte Status per Auswahlliste ändern (offen, in Arbeit, erledigt, wartet, verschoben).
A25: Gelb markiert in der Spalte Herkunft = Vorschlag von Claude (❓), noch nicht entschieden. Ändere Datum, Wer oder Inhalt einfach direkt.
A26: Spalte Warnung zeigt ÜBERFÄLLIG (rot) und bald fällig (orange) automatisch anhand des heutigen Datums.
A27: Blatt „Termine“: die harten Fristen. Blatt „Werbung“: die Werbephasen. Blatt „Offene Fragen“: was Claude von dir braucht.
A28: Quelle: Beschlüsse von Jannik (24.10.2026) und Vault-Notizen. Alles mit Herkunft „Vorschlag ❓“ ist eine Annahme von Claude.
A29: Beispiel einer eigenen Zeile: Nr 999 | Werbung organisch | Reel mit Hinweis posten | 05.11.2026 | 06.11.2026 | Jannik | offen | mittel | Teaser | Vorschlag ❓ | Notiz

Sheet Gesamtplan
A1: Nr | B1: Bereich | C1: Aufgabe | D1: Start | E1: Frist | F1: Tag | G1: Wer | H1: Status | I1: Priorität | J1: Braucht / Abhängigkeit | K1: Herkunft | L1: Notiz | M1: Warnung
A2: 1 | B2: Warteliste & Mail | C2: Warteliste auf der Website erstellt und freigeschaltet | D2: 46319 | E2: 46319 | F2: =CHOOSE(WEEKDAY(E2,2),"Mo","Di","Mi","Do","Fr","Sa","So") -> Sa | G2: Jannik | H2: erledigt | I2: mittel | K2: Beschluss Jannik | M2: =IF(H2="erledigt","",IF(E2<TODAY(),"ÜBERFÄLLIG",IF(E2-TODAY()<=2,"bald fällig","")))
A3: 2 | B3: Warteliste & Mail | C3: Brevo-Warteliste erstellt, Double-Opt-In aktiv | D3: 46319 | E3: 46319 | F3: =CHOOSE(WEEKDAY(E3,2),"Mo","Di","Mi","Do","Fr","Sa","So") -> Sa | G3: Jannik | H3: erledigt | I3: mittel | K3: Beschluss Jannik | M3: =IF(H3="erledigt","",IF(E3<TODAY(),"ÜBERFÄLLIG",IF(E3-TODAY()<=2,"bald fällig","")))
A4: 3 | B4: Produktion | C4: 3 Videos gedreht: I will follow him, Herbei oh ihr Gläubigen, Fill my cup Lord | D4: 46319 | E4: 46319 | F4: =CHOOSE(WEEKDAY(E4,2),"Mo","Di","Mi","Do","Fr","Sa","So") -> Sa | G4: Jannik/David | H4: erledigt | I4: mittel | K4: Beschluss Jannik | M4: =IF(H4="erledigt","",IF(E4<TODAY(),"ÜBERFÄLLIG",IF(E4-TODAY()<=2,"bald fällig","")))
A5: 4 | B5: Gewinnspiel | C5: YouTube-Kommentar-Auswahl-Tool ausgesucht | D5: 46319 | E5: 46319 | F5: =CHOOSE(WEEKDAY(E5,2),"Mo","Di","Mi","Do","Fr","Sa","So") -> Sa | G5: Jannik | H5: erledigt | I5: mittel | K5: Beschluss Jannik | M5: =IF(H5="erledigt","",IF(E5<TODAY(),"ÜBERFÄLLIG",IF(E5-TODAY()<=2,"bald fällig","")))
A6: 5 | B6: Recht & Rechte | C6: Gewerbemeldebestätigung für TikTok besorgt | D6: 46319 | E6: 46319 | F6: =CHOOSE(WEEKDAY(E6,2),"Mo","Di","Mi","Do","Fr","Sa","So") -> Sa | G6: Jannik | H6: erledigt | I6: mittel | K6: Beschluss Jannik | M6: =IF(H6="erledigt","",IF(E6<TODAY(),"ÜBERFÄLLIG",IF(E6-TODAY()<=2,"bald fällig","")))
A7: 6 | B7: Warteliste & Mail | C7: Altliste geprüft: Newsletter mit Konzerten 2027 + Warteliste-Hinweis erlaubt | D7: 46319 | E7: 46319 | F7: =CHOOSE(WEEKDAY(E7,2),"Mo","Di","Mi","Do","Fr","Sa","So") -> Sa | G7: Jannik | H7: erledigt | I7: mittel | K7: Beschluss Jannik | M7: =IF(H7="erledigt","",IF(E7<TODAY(),"ÜBERFÄLLIG",IF(E7-TODAY()<=2,"bald fällig","")))
A8: 7 | B8: Orga & Budget | C8: Konzept, Preise (25 € / 29,99 €), Ablauf, Lose-Modell (1 / 2 Lose), Termine festgelegt | D8: 46319 | E8: 46319 | F8: =CHOOSE(WEEKDAY(E8,2),"Mo","Di","Mi","Do","Fr","Sa","So") -> Sa | G8: Jannik | H8: erledigt | I8: mittel | K8: Beschluss Jannik | M8: =IF(H8="erledigt","",IF(E8<TODAY(),"ÜBERFÄLLIG",IF(E8-TODAY()<=2,"bald fällig","")))
A9: 8 | B9: Orga & Budget | C9: Vault aufgebaut: Planung, Songtabelle, Drehplan, Texte, Impressum, Rechts-Briefing | D9: 46319 | E9: 46319 | F9: =CHOOSE(WEEKDAY(E9,2),"Mo","Di","Mi","Do","Fr","Sa","So") -> Sa | G9: Claude | H9: erledigt | I9: mittel | K9: Claude erledigt | M9: =IF(H9="erledigt","",IF(E9<TODAY(),"ÜBERFÄLLIG",IF(E9-TODAY()<=2,"bald fällig","")))
A10: 9 | B10: Gewinnspiel | C10: Teilnahmebedingungen und Ziehungs-Skript (Entwurf) erstellt | D10: 46319 | E10: 46319 | F10: =CHOOSE(WEEKDAY(E10,2),"Mo","Di","Mi","Do","Fr","Sa","So") -> Sa | G10: Claude | H10: erledigt | I10: mittel | K10: Claude erledigt | M10: =IF(H10="erledigt","",IF(E10<TODAY(),"ÜBERFÄLLIG",IF(E10-TODAY()<=2,"bald fällig","")))
A11: 10 | B11: Warteliste & Mail | C11: Landingpage-Text und 7 Brevo-Mails (Deutsch, Entwurf) geschrieben | D11: 46319 | E11: 46319 | F11: =CHOOSE(WEEKDAY(E11,2),"Mo","Di","Mi","Do","Fr","Sa","So") -> Sa | G11: Claude | H11: erledigt | I11: mittel | K11: Claude erledigt | M11: =IF(H11="erledigt","",IF(E11<TODAY(),"ÜBERFÄLLIG",IF(E11-TODAY()<=2,"bald fällig","")))
A12: 11 | B12: Produktion | C12: Liedliste (alle Lieder, auch die neuen) in den Chat schicken | D12: 46319 | E12: 46320 | F12: =CHOOSE(WEEKDAY(E12,2),"Mo","Di","Mi","Do","Fr","Sa","So") -> So | G12: Jannik | H12: offen | I12: hoch | K12: Blocker | M12: =IF(H12="erledigt","",IF(E12<TODAY(),"ÜBERFÄLLIG",IF(E12-TODAY()<=2,"bald fällig",""))) -> bald fällig
A13: 12 | B13: Warteliste & Mail | C13: Konzertseiten-Text (Konzerte 2027) in den Chat kopieren | D13: 46319 | E13: 46320 | F13: =CHOOSE(WEEKDAY(E13,2),"Mo","Di","Mi","Do","Fr","Sa","So") -> So | G13: Jannik | H13: offen | I13: hoch | K13: Blocker | L13: Claude kann die Homepage nicht öffnen. | M13: =IF(H13="erledigt","",IF(E13<TODAY(),"ÜBERFÄLLIG",IF(E13-TODAY()<=2,"bald fällig",""))) -> bald fällig
A14: 13 | B14: Warteliste & Mail | C14: Landingpage-Link oder -Text der aktuellen Warteliste schicken | D14: 46319 | E14: 46320 | F14: =CHOOSE(WEEKDAY(E14,2),"Mo","Di","Mi","Do","Fr","Sa","So") -> So | G14: Jannik | H14: offen | I14: hoch | K14: Blocker | M14: =IF(H14="erledigt","",IF(E14<TODAY(),"ÜBERFÄLLIG",IF(E14-TODAY()<=2,"bald fällig",""))) -> bald fällig
A15: 14 | B15: Warteliste & Mail | C15: Homepage-Konzertseite: Zugriff für Claude klären (kein Browser in dieser Sitzung); Text kopieren | D15: 46320 | E15: 46320 | F15: =CHOOSE(WEEKDAY(E15,2),"Mo","Di","Mi","Do","Fr","Sa","So") -> So | G15: Jannik | H15: offen | I15: hoch | K15: Blocker | L15: Claude hat in dieser Sitzung keinen Browser-Zugang. | M15: =IF(H15="erledigt","",IF(E15<TODAY(),"ÜBERFÄLLIG",IF(E15-TODAY()<=2,"bald fällig",""))) -> bald fällig
A16: 15 | B16: Orga & Budget | C16: Team festlegen: wer macht was, wie viele Stunden pro Woche | D16: 46319 | E16: 46321 | F16: =CHOOSE(WEEKDAY(E16,2),"Mo","Di","Mi","Do","Fr","Sa","So") -> Mo | G16: Jannik + Eltern | H16: erledigt | I16: hoch | K16: Beschluss Jannik | L16: Ohne Zuständigkeiten stockt alles. Jannik 20 Std./Woche (Social Media, Warteliste, Website/Shop, Konzerte, Videoschnitt). Mutter: Videodreh. Vater: vor der Kamera. Eltern zusammen ca. 10 Std./Woche. | M16: =IF(H16="erledigt","",IF(E16<TODAY(),"ÜBERFÄLLIG",IF(E16-TODAY()<=2,"bald fällig","")))
A17: 16 | B17: Produktion | C17: Dreh-Termine mit David festlegen (Studio Paraguay, ganze Blöcke) | D17: 46319 | E17: 46321 | F17: =CHOOSE(WEEKDAY(E17,2),"Mo","Di","Mi","Do","Fr","Sa","So") -> Mo | G17: Jannik + David | H17: offen | I17: hoch | K17: Blocker | L17: 21 Videos offen, bis 15.11. | M17: =IF(H17="erledigt","",IF(E17<TODAY(),"ÜBERFÄLLIG",IF(E17-TODAY()<=2,"bald fällig",""))) -> bald fällig
A18: 17 | B18: Shop & Technik | C18: Zugangssystem entscheiden: Plugin im Shop oder eigener Server? Wer baut es? | D18: 46319 | E18: 46321 | F18: =CHOOSE(WEEKDAY(E18,2),"Mo","Di","Mi","Do","Fr","Sa","So") -> Mo | G18: Jannik | H18: offen | I18: hoch | J18: Admin-Zugang, Pluginliste | K18: Blocker | L18: Größtes Risiko für Do 29.10. | M18: =IF(H18="erledigt","",IF(E18<TODAY(),"ÜBERFÄLLIG",IF(E18-TODAY()<=2,"bald fällig",""))) -> bald fällig
A19: 18 | B19: Shop & Technik | C19: Admin-Zugang und Umsetzer klären (WordPress/WooCommerce) | D19: 46319 | E19: 46321 | F19: =CHOOSE(WEEKDAY(E19,2),"Mo","Di","Mi","Do","Fr","Sa","So") -> Mo | G19: Jannik | H19: offen | I19: hoch | K19: Beschluss Jannik | M19: =IF(H19="erledigt","",IF(E19<TODAY(),"ÜBERFÄLLIG",IF(E19-TODAY()<=2,"bald fällig",""))) -> bald fällig
A20: 19 | B20: Warteliste & Mail | C20: Absender in Brevo festlegen (Name und Adresse) | D20: 46319 | E20: 46321 | F20: =CHOOSE(WEEKDAY(E20,2),"Mo","Di","Mi","Do","Fr","Sa","So") -> Mo | G20: Jannik | H20: offen | I20: hoch | K20: Beschluss Jannik | L20: Jannik nennt ihn später. | M20: =IF(H20="erledigt","",IF(E20<TODAY(),"ÜBERFÄLLIG",IF(E20-TODAY()<=2,"bald fällig",""))) -> bald fällig
A21: 20 | B21: Recht & Rechte | C21: GEMA und Labels anfragen (Songtabelle, Mail-Entwurf im Vault) | D21: 46319 | E21: 46321 | F21: =CHOOSE(WEEKDAY(E21,2),"Mo","Di","Mi","Do","Fr","Sa","So") -> Mo | G21: Jannik | H21: offen | I21: hoch | J21: Liedliste final | K21: Beschluss Jannik | L21: Antworten dauern Wochen, deshalb sofort. | M21: =IF(H21="erledigt","",IF(E21<TODAY(),"ÜBERFÄLLIG",IF(E21-TODAY()<=2,"bald fällig",""))) -> bald fällig
A22: 21 | B22: Recht & Rechte | C22: GEMA: Lizenz für Bezahlseite auf eigener Webseite klären | D22: 46319 | E22: 46321 | F22: =CHOOSE(WEEKDAY(E22,2),"Mo","Di","Mi","Do","Fr","Sa","So") -> Mo | G22: Jannik | H22: offen | I22: hoch | K22: Vorschlag ❓ (Claude) | M22: =IF(H22="erledigt","",IF(E22<TODAY(),"ÜBERFÄLLIG",IF(E22-TODAY()<=2,"bald fällig",""))) -> bald fällig
A23: 22 | B23: Korea & USA | C23: Mama erinnern: koreanische Community und Mr. Lee ansprechen | D23: 46321 | E23: 46321 | F23: =CHOOSE(WEEKDAY(E23,2),"Mo","Di","Mi","Do","Fr","Sa","So") -> Mo | G23: Jannik | H23: offen | I23: hoch | K23: Beschluss Jannik | L23: Kalendereintrag Mo 26.10. angelegt. | M23: =IF(H23="erledigt","",IF(E23<TODAY(),"ÜBERFÄLLIG",IF(E23-TODAY()<=2,"bald fällig",""))) -> bald fällig
A24: 23 | B24: Produktion | C24: Videoformat entscheiden (16:9 für den Kalender, Kurzvideos hochkant) | D24: 46320 | E24: 46321 | F24: =CHOOSE(WEEKDAY(E24,2),"Mo","Di","Mi","Do","Fr","Sa","So") -> Mo | G24: Jannik | H24: erledigt | I24: mittel | K24: Beschluss Jannik | L24: 16:9 für den Kalender. | M24: =IF(H24="erledigt","",IF(E24<TODAY(),"ÜBERFÄLLIG",IF(E24-TODAY()<=2,"bald fällig","")))
A25: 24 | B25: Orga & Budget | C25: Gesamtbudget festlegen (Tools, Werbung, Preise, Rechtsprüfung, Porto) | D25: 46319 | E25: 46322 | F25: =CHOOSE(WEEKDAY(E25,2),"Mo","Di","Mi","Do","Fr","Sa","So") -> Di | G25: Jannik + Eltern | H25: offen | I25: hoch | K25: Blocker | L25: Jannik wollte nachfragen. | M25: =IF(H25="erledigt","",IF(E25<TODAY(),"ÜBERFÄLLIG",IF(E25-TODAY()<=2,"bald fällig","")))
A26: 25 | B26: Produktion | C26: Songs final festlegen: 10 Lied-Videos + 4 Musikvideos, Playback eigen oder fremd | D26: 46320 | E26: 46322 | F26: =CHOOSE(WEEKDAY(E26,2),"Mo","Di","Mi","Do","Fr","Sa","So") -> Di | G26: Jannik + David | H26: offen | I26: hoch | J26: Liedliste | K26: Blocker | M26: =IF(H26="erledigt","",IF(E26<TODAY(),"ÜBERFÄLLIG",IF(E26-TODAY()<=2,"bald fällig","")))
A27: 26 | B27: Shop & Technik | C27: Produkt „Adventskalender 2026“ im Shop anlegen (25 €, ab 16.11. 29,99 €) | D27: 46322 | E27: 46322 | F27: =CHOOSE(WEEKDAY(E27,2),"Mo","Di","Mi","Do","Fr","Sa","So") -> Di | G27: Jannik | H27: offen | I27: hoch | J27: Zugangssystem | K27: Beschluss Jannik | L27: Aktionspreis zeitlich planen (❓ prüfen). | M27: =IF(H27="erledigt","",IF(E27<TODAY(),"ÜBERFÄLLIG",IF(E27-TODAY()<=2,"bald fällig","")))
A28: 27 | B28: Shop & Technik | C28: PayPal im Shop prüfen, weitere Zahlarten klären | D28: 46322 | E28: 46322 | F28: =CHOOSE(WEEKDAY(E28,2),"Mo","Di","Mi","Do","Fr","Sa","So") -> Di | G28: Jannik | H28: offen | I28: hoch | K28: Beschluss Jannik | M28: =IF(H28="erledigt","",IF(E28<TODAY(),"ÜBERFÄLLIG",IF(E28-TODAY()<=2,"bald fällig","")))
A29: 28 | B29: Werbung organisch | C29: Werbeplan (Kanäle, Rhythmus, Botschaften) final abstimmen | D29: 46320 | E29: 46322 | F29: =CHOOSE(WEEKDAY(E29,2),"Mo","Di","Mi","Do","Fr","Sa","So") -> Di | G29: Jannik + Claude | H29: offen | I29: hoch | J29: Budget | K29: Blocker | L29: Siehe Blatt „Werbung“. | M29: =IF(H29="erledigt","",IF(E29<TODAY(),"ÜBERFÄLLIG",IF(E29-TODAY()<=2,"bald fällig","")))
A30: 29 | B30: Werbung organisch | C30: Teaser-Ausschnitte festlegen (welche Videos/Lieder dürfen öffentlich?) | D30: 46320 | E30: 46322 | F30: =CHOOSE(WEEKDAY(E30,2),"Mo","Di","Mi","Do","Fr","Sa","So") -> Di | G30: Jannik | H30: offen | I30: hoch | J30: Rechteklärung bei geschützten Liedern | K30: Blocker | M30: =IF(H30="erledigt","",IF(E30<TODAY(),"ÜBERFÄLLIG",IF(E30-TODAY()<=2,"bald fällig","")))
A31: 30 | B31: Werbung bezahlt | C31: Werbebudget und Rahmen festlegen (Beispiel: 300–600 € ❓) | D31: 46320 | E31: 46322 | F31: =CHOOSE(WEEKDAY(E31,2),"Mo","Di","Mi","Do","Fr","Sa","So") -> Di | G31: Jannik + Eltern | H31: offen | I31: hoch | J31: Gesamtbudget | K31: Vorschlag ❓ (Claude) | L31: Bisher nicht eingeplant. Zahl ist nur ein Platzhalter. | M31: =IF(H31="erledigt","",IF(E31<TODAY(),"ÜBERFÄLLIG",IF(E31-TODAY()<=2,"bald fällig","")))
A32: 31 | B32: Recht & Rechte | C32: Teaser nur mit rechtefreien oder geklärten Liedern veröffentlichen | D32: 46320 | E32: 46322 | F32: =CHOOSE(WEEKDAY(E32,2),"Mo","Di","Mi","Do","Fr","Sa","So") -> Di | G32: Jannik | H32: offen | I32: hoch | K32: Vorschlag ❓ (Claude) | L32: Geschützte Titel: erst klären. | M32: =IF(H32="erledigt","",IF(E32<TODAY(),"ÜBERFÄLLIG",IF(E32-TODAY()<=2,"bald fällig","")))
A33: 32 | B33: Orga & Budget | C33: Kapazität prüfen: Schnittaufwand pro Video festlegen (Jannik 20 Std./Woche für Social Media, Shop, Warteliste, Schnitt) | D33: 46321 | E33: 46322 | F33: =CHOOSE(WEEKDAY(E33,2),"Mo","Di","Mi","Do","Fr","Sa","So") -> Di | G33: Jannik + Claude | H33: offen | I33: hoch | K33: Vorschlag ❓ (Claude) | L33: Risiko: 24 Videos, tägliche Posts und Shop-Aufbau in 3 Wochen. Videoagent für Rohschnitt nutzen, Vorlagen für Titel/Untertitel. | M33: =IF(H33="erledigt","",IF(E33<TODAY(),"ÜBERFÄLLIG",IF(E33-TODAY()<=2,"bald fällig","")))
A34: 33 | B34: Produktion | C34: 10 Geschichten-Themen mit David abstimmen und festlegen | D34: 46321 | E34: 46323 | F34: =CHOOSE(WEEKDAY(E34,2),"Mo","Di","Mi","Do","Fr","Sa","So") -> Mi | G34: Jannik + David | H34: offen | I34: hoch | J34: Themenvorschläge in [[Adventskalender-Drehplan]] | K34: Vorschlag ❓ (Claude) | M34: =IF(H34="erledigt","",IF(E34<TODAY(),"ÜBERFÄLLIG",IF(E34-TODAY()<=2,"bald fällig","")))
A35: 34 | B35: Produktion | C35: Dreh-Block A: Lieder (gleiche Kameraposition), 4 Videos | D35: 46323 | E35: 46323 | F35: =CHOOSE(WEEKDAY(E35,2),"Mo","Di","Mi","Do","Fr","Sa","So") -> Mi | G35: Mutter (Kamera) + David | H35: offen | I35: hoch | J35: Terminfreigabe David | K35: Vorschlag ❓ (Claude) | L35: Termin ❓ nur Vorschlag. | M35: =IF(H35="erledigt","",IF(E35<TODAY(),"ÜBERFÄLLIG",IF(E35-TODAY()<=2,"bald fällig","")))
A36: 35 | B36: Shop & Technik | C36: Shop-Hinweise: Start 1.12., täglich ein Türchen, späte Käufer sehen alles | D36: 46322 | E36: 46323 | F36: =CHOOSE(WEEKDAY(E36,2),"Mo","Di","Mi","Do","Fr","Sa","So") -> Mi | G36: Jannik + Claude | H36: offen | I36: hoch | K36: Beschluss Jannik | M36: =IF(H36="erledigt","",IF(E36<TODAY(),"ÜBERFÄLLIG",IF(E36-TODAY()<=2,"bald fällig","")))
A37: 36 | B37: Shop & Technik | C37: Bestellmail mit persönlichem Zugangslink einrichten | D37: 46322 | E37: 46323 | F37: =CHOOSE(WEEKDAY(E37,2),"Mo","Di","Mi","Do","Fr","Sa","So") -> Mi | G37: Jannik | H37: offen | I37: hoch | J37: Zugangssystem | K37: Beschluss Jannik | M37: =IF(H37="erledigt","",IF(E37<TODAY(),"ÜBERFÄLLIG",IF(E37-TODAY()<=2,"bald fällig","")))
A38: 37 | B38: Shop & Technik | C38: Landingpage Deutsch veröffentlichen (mit Warteliste und Kaufen-Button) | D38: 46321 | E38: 46323 | F38: =CHOOSE(WEEKDAY(E38,2),"Mo","Di","Mi","Do","Fr","Sa","So") -> Mi | G38: Jannik + Claude | H38: offen | I38: hoch | J38: Link/Text der Warteliste-Seite | K38: Beschluss Jannik | M38: =IF(H38="erledigt","",IF(E38<TODAY(),"ÜBERFÄLLIG",IF(E38-TODAY()<=2,"bald fällig","")))
A39: 38 | B39: Warteliste & Mail | C39: Brevo: Mails 1–3 einrichten (Bestätigung, Willkommen, Verkaufsstart) | D39: 46321 | E39: 46323 | F39: =CHOOSE(WEEKDAY(E39,2),"Mo","Di","Mi","Do","Fr","Sa","So") -> Mi | G39: Jannik | H39: offen | I39: hoch | J39: Absender, Texte | K39: Beschluss Jannik | M39: =IF(H39="erledigt","",IF(E39<TODAY(),"ÜBERFÄLLIG",IF(E39-TODAY()<=2,"bald fällig","")))
A40: 39 | B40: Werbung organisch | C40: Links in Bios setzen (Instagram, TikTok Business-Konto, Facebook, YouTube) auf Landingpage | D40: 46322 | E40: 46323 | F40: =CHOOSE(WEEKDAY(E40,2),"Mo","Di","Mi","Do","Fr","Sa","So") -> Mi | G40: Jannik | H40: offen | I40: hoch | J40: Landingpage | K40: Notion-Plan | L40: Nur der Bio-Link ist klickbar. | M40: =IF(H40="erledigt","",IF(E40<TODAY(),"ÜBERFÄLLIG",IF(E40-TODAY()<=2,"bald fällig","")))
A41: 40 | B41: Werbung organisch | C41: Ankündigungs-Posts Warteliste (Instagram, TikTok, Facebook, YouTube Community) | D41: 46323 | E41: 46323 | F41: =CHOOSE(WEEKDAY(E41,2),"Mo","Di","Mi","Do","Fr","Sa","So") -> Mi | G41: Jannik | H41: offen | I41: hoch | J41: Teaser | K41: Vorschlag ❓ (Claude) | M41: =IF(H41="erledigt","",IF(E41<TODAY(),"ÜBERFÄLLIG",IF(E41-TODAY()<=2,"bald fällig","")))
A42: 41 | B42: Gewinnspiel | C42: Rechtsprüfung beauftragen (Fachanwalt oder Kanzlei, mit Briefing) | D42: 46320 | E42: 46323 | F42: =CHOOSE(WEEKDAY(E42,2),"Mo","Di","Mi","Do","Fr","Sa","So") -> Mi | G42: Jannik | H42: offen | I42: hoch | J42: Briefing im Vault | K42: Beschluss Jannik | L42: Briefing: [[Adventskalender-Rechtsklaerung-Gewinnspiel]] | M42: =IF(H42="erledigt","",IF(E42<TODAY(),"ÜBERFÄLLIG",IF(E42-TODAY()<=2,"bald fällig","")))
A43: 42 | B43: Recht & Rechte | C43: Impressum, Datenschutzerklärung, Widerruf auf Landingpage und Kalenderseite prüfen | D43: 46321 | E43: 46323 | F43: =CHOOSE(WEEKDAY(E43,2),"Mo","Di","Mi","Do","Fr","Sa","So") -> Mi | G43: Jannik + Extern | H43: offen | I43: hoch | K43: Vorschlag ❓ (Claude) | M43: =IF(H43="erledigt","",IF(E43<TODAY(),"ÜBERFÄLLIG",IF(E43-TODAY()<=2,"bald fällig","")))
A44: 43 | B44: Korea & USA | C44: Festlegen: welche Videos bekommen englische und koreanische Fassung (Voice-Over/Untertitel)? | D44: 46321 | E44: 46323 | F44: =CHOOSE(WEEKDAY(E44,2),"Mo","Di","Mi","Do","Fr","Sa","So") -> Mi | G44: Jannik | H44: erledigt | I44: hoch | K44: Beschluss Jannik | L44: Jannik: USA/Korea jetzt planen. Alle Videos, die keine Musik sind (Geschichten, Brief an die Zuschauer): englische und koreanische Fassung. | M44: =IF(H44="erledigt","",IF(E44<TODAY(),"ÜBERFÄLLIG",IF(E44-TODAY()<=2,"bald fällig","")))
A45: 44 | B45: Gewinnspiel | C45: Länderliste (11 Länder) von der Kanzlei prüfen lassen: DE, NL, CZ, FR, CH, AT, LU, BE, Südkorea, USA, Paraguay | D45: 46321 | E45: 46323 | F45: =CHOOSE(WEEKDAY(E45,2),"Mo","Di","Mi","Do","Fr","Sa","So") -> Mi | G45: Jannik + Extern | H45: offen | I45: hoch | J45: Briefing | K45: Beschluss Jannik | L45: Versand und Zoll je Land klären. | M45: =IF(H45="erledigt","",IF(E45<TODAY(),"ÜBERFÄLLIG",IF(E45-TODAY()<=2,"bald fällig","")))
A46: 45 | B46: Produktion | C46: Look abstimmen (hellbraun, rot, grün), Setting, Kleidung | D46: 46321 | E46: 46323 | F46: =CHOOSE(WEEKDAY(E46,2),"Mo","Di","Mi","Do","Fr","Sa","So") -> Mi | G46: Jannik + David | H46: offen | I46: mittel | K46: Beschluss Jannik | L46: Abstimmung mit David offen. | M46: =IF(H46="erledigt","",IF(E46<TODAY(),"ÜBERFÄLLIG",IF(E46-TODAY()<=2,"bald fällig","")))
A47: 46 | B47: Shop & Technik | C47: TESTKAUF mit Zugangslink-Mail durchführen | D47: 46324 | E47: 46324 | F47: =CHOOSE(WEEKDAY(E47,2),"Mo","Di","Mi","Do","Fr","Sa","So") -> Do | G47: Jannik | H47: offen | I47: hoch | J47: Alles oben | K47: Beschluss Jannik | M47: =IF(H47="erledigt","",IF(E47<TODAY(),"ÜBERFÄLLIG",IF(E47-TODAY()<=2,"bald fällig","")))
A48: 47 | B48: Shop & Technik | C48: KAUFEN-BUTTON LIVE (spätester Termin) | D48: 46324 | E48: 46324 | F48: =CHOOSE(WEEKDAY(E48,2),"Mo","Di","Mi","Do","Fr","Sa","So") -> Do | G48: Jannik | H48: offen | I48: hoch | J48: Testkauf | K48: Beschluss Jannik | L48: DEADLINE Donnerstag 29.10. | M48: =IF(H48="erledigt","",IF(E48<TODAY(),"ÜBERFÄLLIG",IF(E48-TODAY()<=2,"bald fällig","")))
A49: 48 | B49: Warteliste & Mail | C49: Newsletter an Altliste schreiben (Konzerte 2027 + Kalender) | D49: 46321 | E49: 46324 | F49: =CHOOSE(WEEKDAY(E49,2),"Mo","Di","Mi","Do","Fr","Sa","So") -> Do | G49: Claude | H49: offen | I49: hoch | J49: Konzertseiten-Text | K49: Beschluss Jannik | M49: =IF(H49="erledigt","",IF(E49<TODAY(),"ÜBERFÄLLIG",IF(E49-TODAY()<=2,"bald fällig","")))
A50: 49 | B50: Warteliste & Mail | C50: Verkaufsstart-Mail an die Warteliste senden | D50: 46324 | E50: 46324 | F50: =CHOOSE(WEEKDAY(E50,2),"Mo","Di","Mi","Do","Fr","Sa","So") -> Do | G50: Jannik | H50: offen | I50: hoch | J50: Kaufen-Button live | K50: Beschluss Jannik | M50: =IF(H50="erledigt","",IF(E50<TODAY(),"ÜBERFÄLLIG",IF(E50-TODAY()<=2,"bald fällig","")))
A51: 50 | B51: Werbung organisch | C51: Teaser-Clips schneiden (hochkant 30–45 Sek.) für Instagram, TikTok, Shorts | D51: 46322 | E51: 46324 | F51: =CHOOSE(WEEKDAY(E51,2),"Mo","Di","Mi","Do","Fr","Sa","So") -> Do | G51: Jannik + Videoagent | H51: offen | I51: hoch | J51: Ausschnitte | K51: Beschluss Jannik | M51: =IF(H51="erledigt","",IF(E51<TODAY(),"ÜBERFÄLLIG",IF(E51-TODAY()<=2,"bald fällig","")))
A52: 51 | B52: Werbung organisch | C52: LAUNCH-Posts auf allen Kanälen: Kalender ist kaufbar (Reel, Story, TikTok, FB, YT-Community) | D52: 46324 | E52: 46324 | F52: =CHOOSE(WEEKDAY(E52,2),"Mo","Di","Mi","Do","Fr","Sa","So") -> Do | G52: Jannik | H52: offen | I52: hoch | J52: Kaufen-Button live | K52: Vorschlag ❓ (Claude) | M52: =IF(H52="erledigt","",IF(E52<TODAY(),"ÜBERFÄLLIG",IF(E52-TODAY()<=2,"bald fällig","")))
A53: 52 | B53: Recht & Rechte | C53: AGB und Widerruf für digitale Inhalte mit späterem Start prüfen lassen | D53: 46321 | E53: 46324 | F53: =CHOOSE(WEEKDAY(E53,2),"Mo","Di","Mi","Do","Fr","Sa","So") -> Do | G53: Jannik + Extern | H53: offen | I53: hoch | K53: Vorschlag ❓ (Claude) | M53: =IF(H53="erledigt","",IF(E53<TODAY(),"ÜBERFÄLLIG",IF(E53-TODAY()<=2,"bald fällig","")))
A54: 53 | B54: Produktion | C54: Skript „Brief an die Zuschauer“ schreiben | D54: 46321 | E54: 46324 | F54: =CHOOSE(WEEKDAY(E54,2),"Mo","Di","Mi","Do","Fr","Sa","So") -> Do | G54: Claude | H54: offen | I54: mittel | J54: Themen | K54: Vorschlag ❓ (Claude) | M54: =IF(H54="erledigt","",IF(E54<TODAY(),"ÜBERFÄLLIG",IF(E54-TODAY()<=2,"bald fällig","")))
A55: 54 | B55: Produktion | C55: Storyboards für die 4 Musikvideos (Real + Higgsfield) | D55: 46321 | E55: 46325 | F55: =CHOOSE(WEEKDAY(E55,2),"Mo","Di","Mi","Do","Fr","Sa","So") -> Fr | G55: Claude + Jannik | H55: offen | I55: hoch | J55: Songs final | K55: Vorschlag ❓ (Claude) | M55: =IF(H55="erledigt","",IF(E55<TODAY(),"ÜBERFÄLLIG",IF(E55-TODAY()<=2,"bald fällig","")))
A56: 55 | B56: Produktion | C56: Dreh-Block B: Lieder + erste Geschichten | D56: 46325 | E56: 46325 | F56: =CHOOSE(WEEKDAY(E56,2),"Mo","Di","Mi","Do","Fr","Sa","So") -> Fr | G56: Mutter (Kamera) + David | H56: offen | I56: hoch | K56: Vorschlag ❓ (Claude) | L56: Termin ❓ | M56: =IF(H56="erledigt","",IF(E56<TODAY(),"ÜBERFÄLLIG",IF(E56-TODAY()<=2,"bald fällig","")))
A57: 56 | B57: Shop & Technik | C57: Videohoster und Unterdomain wählen (z. B. advent.davids-panparadies.de) | D57: 46321 | E57: 46325 | F57: =CHOOSE(WEEKDAY(E57,2),"Mo","Di","Mi","Do","Fr","Sa","So") -> Fr | G57: Jannik | H57: offen | I57: hoch | K57: Vorschlag ❓ (Claude) | M57: =IF(H57="erledigt","",IF(E57<TODAY(),"ÜBERFÄLLIG",IF(E57-TODAY()<=2,"bald fällig","")))
A58: 57 | B58: Warteliste & Mail | C58: Newsletter an die Altliste versenden | D58: 46325 | E58: 46325 | F58: =CHOOSE(WEEKDAY(E58,2),"Mo","Di","Mi","Do","Fr","Sa","So") -> Fr | G58: Jannik | H58: offen | I58: hoch | J58: Kaufen-Button live | K58: Beschluss Jannik | M58: =IF(H58="erledigt","",IF(E58<TODAY(),"ÜBERFÄLLIG",IF(E58-TODAY()<=2,"bald fällig","")))
A59: 58 | B59: Werbung bezahlt | C59: Meta-Business- und Anzeigenkonto prüfen/einrichten (Instagram + Facebook) | D59: 46322 | E59: 46325 | F59: =CHOOSE(WEEKDAY(E59,2),"Mo","Di","Mi","Do","Fr","Sa","So") -> Fr | G59: Jannik | H59: offen | I59: hoch | J59: Zahlungsmittel | K59: Vorschlag ❓ (Claude) | M59: =IF(H59="erledigt","",IF(E59<TODAY(),"ÜBERFÄLLIG",IF(E59-TODAY()<=2,"bald fällig","")))
A60: 59 | B60: Werbung bezahlt | C60: Tracking und Einwilligung (Cookie-Banner, Pixel) rechtlich prüfen, UTM-Links erstellen | D60: 46322 | E60: 46325 | F60: =CHOOSE(WEEKDAY(E60,2),"Mo","Di","Mi","Do","Fr","Sa","So") -> Fr | G60: Jannik + Extern | H60: offen | I60: hoch | J60: Datenschutz | K60: Vorschlag ❓ (Claude) | M60: =IF(H60="erledigt","",IF(E60<TODAY(),"ÜBERFÄLLIG",IF(E60-TODAY()<=2,"bald fällig","")))
A61: 60 | B61: Werbung organisch | C61: YouTube: Link zum Kalender in die Beschreibung der meistgesehenen Videos + angepinnter Kommentar | D61: 46324 | E61: 46326 | F61: =CHOOSE(WEEKDAY(E61,2),"Mo","Di","Mi","Do","Fr","Sa","So") -> Sa | G61: Jannik | H61: offen | I61: hoch | J61: Landingpage | K61: Vorschlag ❓ (Claude) | L61: Kanal hat ca. 127.900 Abos, stärkste Reichweite. | M61: =IF(H61="erledigt","",IF(E61<TODAY(),"ÜBERFÄLLIG",IF(E61-TODAY()<=2,"bald fällig","")))
A62: 61 | B62: Werbung bezahlt | C62: Anzeigen-Texte und -Bilder erstellen (Deutsch) | D62: 46323 | E62: 46326 | F62: =CHOOSE(WEEKDAY(E62,2),"Mo","Di","Mi","Do","Fr","Sa","So") -> Sa | G62: Claude + Jannik | H62: offen | I62: hoch | J62: Teaser | K62: Vorschlag ❓ (Claude) | M62: =IF(H62="erledigt","",IF(E62<TODAY(),"ÜBERFÄLLIG",IF(E62-TODAY()<=2,"bald fällig","")))
A63: 62 | B63: Werbung organisch | C63: WhatsApp-Broadcast / Familie, Freunde, Gemeinden bitten zu teilen | D63: 46324 | E63: 46326 | F63: =CHOOSE(WEEKDAY(E63,2),"Mo","Di","Mi","Do","Fr","Sa","So") -> Sa | G63: Jannik + Eltern | H63: offen | I63: mittel | K63: Vorschlag ❓ (Claude) | M63: =IF(H63="erledigt","",IF(E63<TODAY(),"ÜBERFÄLLIG",IF(E63-TODAY()<=2,"bald fällig","")))
A64: 63 | B64: Werbung organisch | C64: Facebook-Seite DavidsPanfloete: Launch-Post + Hinweis in Gruppen (nur wo erlaubt) | D64: 46324 | E64: 46326 | F64: =CHOOSE(WEEKDAY(E64,2),"Mo","Di","Mi","Do","Fr","Sa","So") -> Sa | G64: Jannik | H64: offen | I64: mittel | K64: Vorschlag ❓ (Claude) | M64: =IF(H64="erledigt","",IF(E64<TODAY(),"ÜBERFÄLLIG",IF(E64-TODAY()<=2,"bald fällig","")))
A65: 64 | B65: Korea & USA | C65: Koreanische Übersetzerin einplanen (Texte, Voice-Over, Zeitfenster) | D65: 46323 | E65: 46327 | F65: =CHOOSE(WEEKDAY(E65,2),"Mo","Di","Mi","Do","Fr","Sa","So") -> So | G65: Jannik | H65: offen | I65: hoch | K65: Beschluss Jannik | M65: =IF(H65="erledigt","",IF(E65<TODAY(),"ÜBERFÄLLIG",IF(E65-TODAY()<=2,"bald fällig","")))
A66: 65 | B66: Orga & Budget | C66: Wöchentlicher Stand-Check mit den Eltern (Sonntag): Videos, Verkauf, Werbung | D66: 46327 | E66: 46327 | F66: =CHOOSE(WEEKDAY(E66,2),"Mo","Di","Mi","Do","Fr","Sa","So") -> So | G66: Jannik | H66: offen | I66: mittel | K66: Vorschlag ❓ (Claude) | L66: Termin und Rhythmus ❓ anpassen. | M66: =IF(H66="erledigt","",IF(E66<TODAY(),"ÜBERFÄLLIG",IF(E66-TODAY()<=2,"bald fällig","")))
A67: 66 | B67: Produktion | C67: Higgsfield: Bedingungen und Preise prüfen, dann 3-Tage-Test | D67: 46321 | E67: 46327 | F67: =CHOOSE(WEEKDAY(E67,2),"Mo","Di","Mi","Do","Fr","Sa","So") -> So | G67: Jannik | H67: offen | I67: mittel | J67: Bedingungen vorher lesen | K67: Beschluss Jannik | L67: Kosten pro Clip notieren. | M67: =IF(H67="erledigt","",IF(E67<TODAY(),"ÜBERFÄLLIG",IF(E67-TODAY()<=2,"bald fällig","")))
A68: 67 | B68: Warteliste & Mail | C68: Brevo: Käufer taggen (Etikett „Käufer“), Warteliste und Käufer trennen | D68: 46324 | E68: 46327 | F68: =CHOOSE(WEEKDAY(E68,2),"Mo","Di","Mi","Do","Fr","Sa","So") -> So | G68: Jannik | H68: offen | I68: mittel | J68: Shop-Anbindung | K68: Vorschlag ❓ (Claude) | M68: =IF(H68="erledigt","",IF(E68<TODAY(),"ÜBERFÄLLIG",IF(E68-TODAY()<=2,"bald fällig","")))
A69: 68 | B69: Produktion | C69: Dreh-Block C: Geschichten | D69: 46328 | E69: 46328 | F69: =CHOOSE(WEEKDAY(E69,2),"Mo","Di","Mi","Do","Fr","Sa","So") -> Mo | G69: Mutter (Kamera) + David | H69: offen | I69: hoch | K69: Vorschlag ❓ (Claude) | L69: Termin ❓ | M69: =IF(H69="erledigt","",IF(E69<TODAY(),"ÜBERFÄLLIG",IF(E69-TODAY()<=2,"bald fällig","")))
A70: 69 | B70: Recht & Rechte | C70: GEMA/Label nachfassen | D70: 46328 | E70: 46328 | F70: =CHOOSE(WEEKDAY(E70,2),"Mo","Di","Mi","Do","Fr","Sa","So") -> Mo | G70: Jannik | H70: offen | I70: hoch | K70: Vorschlag ❓ (Claude) | M70: =IF(H70="erledigt","",IF(E70<TODAY(),"ÜBERFÄLLIG",IF(E70-TODAY()<=2,"bald fällig","")))
A71: 70 | B71: Gewinnspiel | C71: Teilnahmebedingungen: Platzhalter ausfüllen (Länder, Alter, Uhrzeit, Plattform) | D71: 46327 | E71: 46329 | F71: =CHOOSE(WEEKDAY(E71,2),"Mo","Di","Mi","Do","Fr","Sa","So") -> Di | G71: Jannik + Claude | H71: in Arbeit | I71: hoch | J71: Entscheidungen | K71: Beschluss Jannik | L71: Entschieden: Mindestalter 18, Länderliste (11 Länder), Live auf YouTube um 14 Uhr DE, Kauf zählt ab Verkaufsstart bis Ziehungsbeginn. Offen: Anschriftsformulierung, Zoll. | M71: =IF(H71="erledigt","",IF(E71<TODAY(),"ÜBERFÄLLIG",IF(E71-TODAY()<=2,"bald fällig","")))
A72: 71 | B72: Produktion | C72: Dreh-Block D: Geschichten | D72: 46330 | E72: 46330 | F72: =CHOOSE(WEEKDAY(E72,2),"Mo","Di","Mi","Do","Fr","Sa","So") -> Mi | G72: Mutter (Kamera) + David | H72: offen | I72: hoch | K72: Vorschlag ❓ (Claude) | L72: Termin ❓ | M72: =IF(H72="erledigt","",IF(E72<TODAY(),"ÜBERFÄLLIG",IF(E72-TODAY()<=2,"bald fällig","")))
A73: 72 | B73: Korea & USA | C73: Englische Landingpage und Mails schreiben | D73: 46328 | E73: 46331 | F73: =CHOOSE(WEEKDAY(E73,2),"Mo","Di","Mi","Do","Fr","Sa","So") -> Do | G73: Claude | H73: offen | I73: hoch | J73: Deutsche Texte final | K73: Vorschlag ❓ (Claude) | M73: =IF(H73="erledigt","",IF(E73<TODAY(),"ÜBERFÄLLIG",IF(E73-TODAY()<=2,"bald fällig","")))
A74: 73 | B74: Shop & Technik | C74: Cron-Job auf der Website zweckbestimmen und aktivieren (z. B. tägliche Mail) | D74: 46328 | E74: 46331 | F74: =CHOOSE(WEEKDAY(E74,2),"Mo","Di","Mi","Do","Fr","Sa","So") -> Do | G74: Jannik | H74: offen | I74: mittel | K74: Beschluss Jannik | M74: =IF(H74="erledigt","",IF(E74<TODAY(),"ÜBERFÄLLIG",IF(E74-TODAY()<=2,"bald fällig","")))
A75: 74 | B75: Gewinnspiel | C75: Bestände prüfen: 12× „Ewigkeit“, 3 Pakete à 6 CDs, 2×2 Konzert-Gutscheine | D75: 46328 | E75: 46331 | F75: =CHOOSE(WEEKDAY(E75,2),"Mo","Di","Mi","Do","Fr","Sa","So") -> Do | G75: Jannik | H75: offen | I75: mittel | J75: Lager | K75: Beschluss Jannik | M75: =IF(H75="erledigt","",IF(E75<TODAY(),"ÜBERFÄLLIG",IF(E75-TODAY()<=2,"bald fällig","")))
A76: 75 | B76: Produktion | C76: Dreh-Block E: Musikvideos (Realdreh-Teil) | D76: 46332 | E76: 46332 | F76: =CHOOSE(WEEKDAY(E76,2),"Mo","Di","Mi","Do","Fr","Sa","So") -> Fr | G76: Mutter (Kamera) + David | H76: offen | I76: hoch | J76: Storyboards | K76: Vorschlag ❓ (Claude) | L76: Termin ❓ | M76: =IF(H76="erledigt","",IF(E76<TODAY(),"ÜBERFÄLLIG",IF(E76-TODAY()<=2,"bald fällig","")))
A77: 76 | B77: Shop & Technik | C77: Rückerstattung: Zugang sperren, Käufer-Bonus entfernen (Ablauf festlegen) | D77: 46329 | E77: 46332 | F77: =CHOOSE(WEEKDAY(E77,2),"Mo","Di","Mi","Do","Fr","Sa","So") -> Fr | G77: Jannik | H77: offen | I77: mittel | K77: Vorschlag ❓ (Claude) | M77: =IF(H77="erledigt","",IF(E77<TODAY(),"ÜBERFÄLLIG",IF(E77-TODAY()<=2,"bald fällig","")))
A78: 77 | B78: Werbung organisch | C78: Behind-the-Scenes-Clips von den Dreh-Blöcken posten | D78: 46323 | E78: 46332 | F78: =CHOOSE(WEEKDAY(E78,2),"Mo","Di","Mi","Do","Fr","Sa","So") -> Fr | G78: Jannik | H78: offen | I78: mittel | K78: Vorschlag ❓ (Claude) | M78: =IF(H78="erledigt","",IF(E78<TODAY(),"ÜBERFÄLLIG",IF(E78-TODAY()<=2,"bald fällig","")))
A79: 78 | B79: Recht & Rechte | C79: Steuerberater: Gewinne, Umsatzsteuer (digitale Produkte weltweit), Werbekosten | D79: 46329 | E79: 46332 | F79: =CHOOSE(WEEKDAY(E79,2),"Mo","Di","Mi","Do","Fr","Sa","So") -> Fr | G79: Jannik | H79: offen | I79: mittel | K79: Vorschlag ❓ (Claude) | M79: =IF(H79="erledigt","",IF(E79<TODAY(),"ÜBERFÄLLIG",IF(E79-TODAY()<=2,"bald fällig","")))
A80: 79 | B80: Werbung organisch | C80: Lokale Presse / Pressemitteilung (z. B. Oberberg) und Panflöten-Community anschreiben | D80: 46328 | E80: 46332 | F80: =CHOOSE(WEEKDAY(E80,2),"Mo","Di","Mi","Do","Fr","Sa","So") -> Fr | G80: Jannik | H80: offen | I80: niedrig | K80: Vorschlag ❓ (Claude) | L80: Ob das passt ❓ entscheiden. | M80: =IF(H80="erledigt","",IF(E80<TODAY(),"ÜBERFÄLLIG",IF(E80-TODAY()<=2,"bald fällig","")))
A81: 80 | B81: Produktion | C81: Schnitt Lied-Videos (7 offen + 3 gedrehte) | D81: 46324 | E81: 46334 | F81: =CHOOSE(WEEKDAY(E81,2),"Mo","Di","Mi","Do","Fr","Sa","So") -> So | G81: Jannik + Videoagent | H81: offen | I81: hoch | J81: Rohmaterial | K81: Beschluss Jannik | L81: Wer schneidet? ❓ | M81: =IF(H81="erledigt","",IF(E81<TODAY(),"ÜBERFÄLLIG",IF(E81-TODAY()<=2,"bald fällig","")))
A82: 81 | B82: Shop & Technik | C82: Kalenderseite bauen (Prototyp → echte Version, 24 Türchen, Datum-Freischaltung) | D82: 46325 | E82: 46334 | F82: =CHOOSE(WEEKDAY(E82,2),"Mo","Di","Mi","Do","Fr","Sa","So") -> So | G82: Claude + Umsetzer | H82: offen | I82: hoch | J82: Hoster, Zugangssystem | K82: Vorschlag ❓ (Claude) | M82: =IF(H82="erledigt","",IF(E82<TODAY(),"ÜBERFÄLLIG",IF(E82-TODAY()<=2,"bald fällig","")))
A83: 82 | B83: Orga & Budget | C83: Wöchentlicher Stand-Check mit den Eltern (Sonntag): Videos, Verkauf, Werbung | D83: 46334 | E83: 46334 | F83: =CHOOSE(WEEKDAY(E83,2),"Mo","Di","Mi","Do","Fr","Sa","So") -> So | G83: Jannik | H83: offen | I83: mittel | K83: Vorschlag ❓ (Claude) | L83: Termin und Rhythmus ❓ anpassen. | M83: =IF(H83="erledigt","",IF(E83<TODAY(),"ÜBERFÄLLIG",IF(E83-TODAY()<=2,"bald fällig","")))
A84: 83 | B84: Werbung bezahlt | C84: Auswertung Kampagnen (Klicks, Kosten pro Kauf) und Anpassung | D84: 46334 | E84: 46334 | F84: =CHOOSE(WEEKDAY(E84,2),"Mo","Di","Mi","Do","Fr","Sa","So") -> So | G84: Jannik + Claude | H84: offen | I84: mittel | J84: Daten | K84: Vorschlag ❓ (Claude) | M84: =IF(H84="erledigt","",IF(E84<TODAY(),"ÜBERFÄLLIG",IF(E84-TODAY()<=2,"bald fällig","")))
A85: 84 | B85: Gewinnspiel | C85: Live-Plattform (YouTube/TikTok) und Uhrzeit (12 oder 14 Uhr DE) festlegen | D85: 46327 | E85: 46334 | F85: =CHOOSE(WEEKDAY(E85,2),"Mo","Di","Mi","Do","Fr","Sa","So") -> So | G85: Jannik + David | H85: erledigt | I85: mittel | K85: Beschluss Jannik | L85: YouTube, 14 Uhr deutsche Zeit (10 Uhr Paraguay, 22 Uhr Korea). | M85: =IF(H85="erledigt","",IF(E85<TODAY(),"ÜBERFÄLLIG",IF(E85-TODAY()<=2,"bald fällig","")))
A86: 85 | B86: Korea & USA | C86: Pilot: 1 Video mit koreanischem Voice-Over als Test | D86: 46329 | E86: 46334 | F86: =CHOOSE(WEEKDAY(E86,2),"Mo","Di","Mi","Do","Fr","Sa","So") -> So | G86: Übersetzerin + Jannik | H86: offen | I86: mittel | K86: Vorschlag ❓ (Claude) | M86: =IF(H86="erledigt","",IF(E86<TODAY(),"ÜBERFÄLLIG",IF(E86-TODAY()<=2,"bald fällig","")))
A87: 86 | B87: Produktion | C87: Higgsfield-Clips für die 4 Musikvideos erzeugen | D87: 46328 | E87: 46335 | F87: =CHOOSE(WEEKDAY(E87,2),"Mo","Di","Mi","Do","Fr","Sa","So") -> Mo | G87: Jannik | H87: offen | I87: hoch | J87: Testabo, Storyboards | K87: Beschluss Jannik | M87: =IF(H87="erledigt","",IF(E87<TODAY(),"ÜBERFÄLLIG",IF(E87-TODAY()<=2,"bald fällig","")))
A88: 87 | B88: Korea & USA | C88: Kanäle für Korea und USA festlegen (KakaoTalk, YouTube, Facebook-Gruppen ❓) | D88: 46328 | E88: 46335 | F88: =CHOOSE(WEEKDAY(E88,2),"Mo","Di","Mi","Do","Fr","Sa","So") -> Mo | G88: Mama + Jannik | H88: offen | I88: mittel | J88: Mr. Lee | K88: Vorschlag ❓ (Claude) | M88: =IF(H88="erledigt","",IF(E88<TODAY(),"ÜBERFÄLLIG",IF(E88-TODAY()<=2,"bald fällig","")))
A89: 88 | B89: Shop & Technik | C89: Zugriffsprüfung auf dem Server (Token), Videos geschützt einbetten | D89: 46328 | E89: 46336 | F89: =CHOOSE(WEEKDAY(E89,2),"Mo","Di","Mi","Do","Fr","Sa","So") -> Di | G89: Umsetzer | H89: offen | I89: hoch | J89: Kalenderseite | K89: Vorschlag ❓ (Claude) | L89: Prototyp prüft nur im Browser, nicht sicher. | M89: =IF(H89="erledigt","",IF(E89<TODAY(),"ÜBERFÄLLIG",IF(E89-TODAY()<=2,"bald fällig","")))
A90: 89 | B90: Korea & USA | C90: Koreanische Landingpage und Mails (Entwurf Claude, Übersetzerin prüft) | D90: 46331 | E90: 46336 | F90: =CHOOSE(WEEKDAY(E90,2),"Mo","Di","Mi","Do","Fr","Sa","So") -> Di | G90: Claude + Übersetzerin | H90: offen | I90: hoch | K90: Vorschlag ❓ (Claude) | M90: =IF(H90="erledigt","",IF(E90<TODAY(),"ÜBERFÄLLIG",IF(E90-TODAY()<=2,"bald fällig","")))
A91: 90 | B91: Warteliste & Mail | C91: Erinnerungs-Mail „Noch 4 Tage Early Bird“ planen und senden | D91: 46336 | E91: 46337 | F91: =CHOOSE(WEEKDAY(E91,2),"Mo","Di","Mi","Do","Fr","Sa","So") -> Mi | G91: Jannik | H91: offen | I91: hoch | K91: Vorschlag ❓ (Claude) | M91: =IF(H91="erledigt","",IF(E91<TODAY(),"ÜBERFÄLLIG",IF(E91-TODAY()<=2,"bald fällig","")))
A92: 91 | B92: Produktion | C92: Schnitt Geschichten-Videos (10) | D92: 46329 | E92: 46338 | F92: =CHOOSE(WEEKDAY(E92,2),"Mo","Di","Mi","Do","Fr","Sa","So") -> Do | G92: Jannik + Videoagent | H92: offen | I92: hoch | J92: Dreh C/D | K92: Beschluss Jannik | M92: =IF(H92="erledigt","",IF(E92<TODAY(),"ÜBERFÄLLIG",IF(E92-TODAY()<=2,"bald fällig","")))
A93: 92 | B93: Recht & Rechte | C93: GEMA/Label zweites Nachfassen; bei Ablehnung Ersatztitel wählen | D93: 46335 | E93: 46338 | F93: =CHOOSE(WEEKDAY(E93,2),"Mo","Di","Mi","Do","Fr","Sa","So") -> Do | G93: Jannik + David | H93: offen | I93: hoch | J93: Antworten | K93: Vorschlag ❓ (Claude) | M93: =IF(H93="erledigt","",IF(E93<TODAY(),"ÜBERFÄLLIG",IF(E93-TODAY()<=2,"bald fällig","")))
A94: 93 | B94: Gewinnspiel | C94: Konzert-Gutschein erstellen (Code, 1 Jahr, einmal einlösbar, Einlass-Regel) | D94: 46331 | E94: 46338 | F94: =CHOOSE(WEEKDAY(E94,2),"Mo","Di","Mi","Do","Fr","Sa","So") -> Do | G94: Jannik + Claude | H94: offen | I94: mittel | K94: Beschluss Jannik | M94: =IF(H94="erledigt","",IF(E94<TODAY(),"ÜBERFÄLLIG",IF(E94-TODAY()<=2,"bald fällig","")))
A95: 94 | B95: Produktion | C95: Weiteres Format ausarbeiten (Ideen sammeln, z. B. Kommentar-Antwort-Sessions) | D95: 46324 | E95: 46338 | F95: =CHOOSE(WEEKDAY(E95,2),"Mo","Di","Mi","Do","Fr","Sa","So") -> Do | G95: Jannik + Claude | H95: offen | I95: niedrig | K95: Beschluss Jannik | M95: =IF(H95="erledigt","",IF(E95<TODAY(),"ÜBERFÄLLIG",IF(E95-TODAY()<=2,"bald fällig","")))
A96: 95 | B96: Produktion | C96: Schnitt Musikvideos (4) | D96: 46333 | E96: 46340 | F96: =CHOOSE(WEEKDAY(E96,2),"Mo","Di","Mi","Do","Fr","Sa","So") -> Sa | G96: Jannik + Videoagent | H96: offen | I96: hoch | J96: Dreh E, Higgsfield | K96: Beschluss Jannik | M96: =IF(H96="erledigt","",IF(E96<TODAY(),"ÜBERFÄLLIG",IF(E96-TODAY()<=2,"bald fällig","")))
A97: 96 | B97: Produktion | C97: Thumbnails/Titelbilder für alle 24 Türchen | D97: 46334 | E97: 46340 | F97: =CHOOSE(WEEKDAY(E97,2),"Mo","Di","Mi","Do","Fr","Sa","So") -> Sa | G97: Claude + Jannik | H97: offen | I97: mittel | K97: Vorschlag ❓ (Claude) | M97: =IF(H97="erledigt","",IF(E97<TODAY(),"ÜBERFÄLLIG",IF(E97-TODAY()<=2,"bald fällig","")))
A98: 97 | B98: Produktion | C98: ALLE 24 Videos gedreht und geschnitten | D98: 46341 | E98: 46341 | F98: =CHOOSE(WEEKDAY(E98,2),"Mo","Di","Mi","Do","Fr","Sa","So") -> So | G98: Jannik | H98: offen | I98: hoch | J98: Alle Blöcke | K98: Beschluss Jannik | L98: Harte Frist (Early-Bird-Ende, Material bis 2. Novemberwoche). | M98: =IF(H98="erledigt","",IF(E98<TODAY(),"ÜBERFÄLLIG",IF(E98-TODAY()<=2,"bald fällig","")))
A99: 98 | B99: Warteliste & Mail | C99: Mail „Letzter Tag Early Bird“ senden | D99: 46341 | E99: 46341 | F99: =CHOOSE(WEEKDAY(E99,2),"Mo","Di","Mi","Do","Fr","Sa","So") -> So | G99: Jannik | H99: offen | I99: hoch | K99: Vorschlag ❓ (Claude) | M99: =IF(H99="erledigt","",IF(E99<TODAY(),"ÜBERFÄLLIG",IF(E99-TODAY()<=2,"bald fällig","")))
A100: 99 | B100: Werbung organisch | C100: Countdown-Posts Early Bird: noch 7 Tage, 3 Tage, letzter Tag | D100: 46334 | E100: 46341 | F100: =CHOOSE(WEEKDAY(E100,2),"Mo","Di","Mi","Do","Fr","Sa","So") -> So | G100: Jannik | H100: offen | I100: hoch | K100: Vorschlag ❓ (Claude) | M100: =IF(H100="erledigt","",IF(E100<TODAY(),"ÜBERFÄLLIG",IF(E100-TODAY()<=2,"bald fällig","")))
...

Sheet Termine
A1: Datum | B1: Tag | C1: Termin | D1: Art | E1: Tage bis dahin
A2: 46321 | B2: =CHOOSE(WEEKDAY(A2,2),"Mo","Di","Mi","Do","Fr","Sa","So") -> Mo | C2: Mama erinnern (Mr. Lee), GEMA-Anfrage, Team und Budget festlegen | D2: Aufgabe | E2: =A2-TODAY() -> 2
A3: 46324 | B3: =CHOOSE(WEEKDAY(A3,2),"Mo","Di","Mi","Do","Fr","Sa","So") -> Do | C3: KAUFEN-BUTTON LIVE (spätester Termin), Testkauf | D3: Harte Frist | E3: =A3-TODAY() -> 5
A4: 46325 | B4: =CHOOSE(WEEKDAY(A4,2),"Mo","Di","Mi","Do","Fr","Sa","So") -> Fr | C4: Newsletter an die Altliste | D4: Aufgabe | E4: =A4-TODAY() -> 6
A5: 46341 | B5: =CHOOSE(WEEKDAY(A5,2),"Mo","Di","Mi","Do","Fr","Sa","So") -> So | C5: Alle 24 Videos fertig, letzter Tag Early Bird (25 €) | D5: Harte Frist | E5: =A5-TODAY() -> 22
A6: 46342 | B6: =CHOOSE(WEEKDAY(A6,2),"Mo","Di","Mi","Do","Fr","Sa","So") -> Mo | C6: Preis ab heute 29,99 € | D6: Preisänderung | E6: =A6-TODAY() -> 23
A7: 46355 | B7: =CHOOSE(WEEKDAY(A7,2),"Mo","Di","Mi","Do","Fr","Sa","So") -> So | C7: 1. Advent: YouTube-Musikvideo 1, Gewinnspiel 1 (12 oder 14 Uhr DE) | D7: Harte Frist | E7: =A7-TODAY() -> 36
A8: 46356 | B8: =CHOOSE(WEEKDAY(A8,2),"Mo","Di","Mi","Do","Fr","Sa","So") -> Mo | C8: Mail „Morgen Türchen 1“ | D8: Aufgabe | E8: =A8-TODAY() -> 37
A9: 46357 | B9: =CHOOSE(WEEKDAY(A9,2),"Mo","Di","Mi","Do","Fr","Sa","So") -> Di | C9: KALENDER STARTET: Türchen 1 | D9: Harte Frist | E9: =A9-TODAY() -> 38
A10: 46362 | B10: =CHOOSE(WEEKDAY(A10,2),"Mo","Di","Mi","Do","Fr","Sa","So") -> So | C10: 2. Advent: Live, Ziehung, Musikvideo-Türchen 6 | D10: Harte Frist | E10: =A10-TODAY() -> 43
A11: 46369 | B11: =CHOOSE(WEEKDAY(A11,2),"Mo","Di","Mi","Do","Fr","Sa","So") -> So | C11: 3. Advent: Live, Ziehung, Musikvideo-Türchen 13 | D11: Harte Frist | E11: =A11-TODAY() -> 50
A12: 46376 | B12: =CHOOSE(WEEKDAY(A12,2),"Mo","Di","Mi","Do","Fr","Sa","So") -> So | C12: 4. Advent: Live, Ziehung, 40 % CD-Rabatt, Musikvideo-Türchen 20 | D12: Harte Frist | E12: =A12-TODAY() -> 57
A13: 46380 | B13: =CHOOSE(WEEKDAY(A13,2),"Mo","Di","Mi","Do","Fr","Sa","So") -> Do | C13: Finale: Türchen 24, große Ziehung | D13: Harte Frist | E13: =A13-TODAY() -> 61

Sheet Werbung
A1: Phase | B1: Zeitraum | C1: Ziel | D1: Kanäle | E1: Inhalte / Ideen | F1: Messgröße (Beispiel ❓) | G1: Budget ❓
A2: 1 Teaser und Warteliste | B2: 24.10.–28.10. | C2: Warteliste füllen, Aufmerksamkeit | D2: Instagram, TikTok, Facebook, YouTube Community, Altliste, WhatsApp | E2: Teaser-Clips (30–45 Sek.), Behind the Scenes vom Dreh, „Trag dich ein“-Post, Bio-Links auf Landingpage | F2: Neue Wartelisten-Einträge | G2: 0 € (organisch)
A3: 2 Launch | B3: 29.10.–1.11. | C3: Erste Käufer, Early Bird | D3: Alle Kanäle, YouTube-Beschreibung und angepinnter Kommentar, Newsletter Altliste 30.10., Verkaufsstart-Mail | E3: Launch-Reel, Story mit Link, YouTube Community-Post, Erklärvideo „So funktioniert der Kalender“ | F3: Käufe, Klicks auf Landingpage | G3: Start Anzeigen ❓
A4: 3 Early-Bird-Druck | B4: 2.11.–15.11. | C4: Käufe vor dem 15.11. | D4: Meta-Anzeigen (Instagram/Facebook), YouTube-Anzeige ❓, organische Posts, Mails 11.11. und 15.11. | E4: Countdown (7 Tage, 3 Tage, letzter Tag), Social Proof (erste Reaktionen), Vorschau auf Türchen, Rabatt-Hinweis 25 € statt 29,99 € | F4: Käufe pro Tag, Kosten pro Kauf | G4: z. B. 150–300 € ❓
A5: 4 Nachlaunch + Korea/USA | B5: 16.11.–28.11. | C5: Weiter verkaufen, Korea und USA öffnen | D5: Meta-Anzeigen DE/KR/US ❓, Korea-Community über Mr. Lee, organische Posts | E5: „Noch 29,99 €, Start am 1.12.“, koreanische und englische Landingpage, Gewinnspiel-Vorschau, Behind the Scenes | F5: Käufe nach Land | G5: z. B. 150–300 € ❓
A6: 5 Countdown | B6: 25.11.–30.11. | C6: Spannung vor dem Start | D6: Stories, Reels, Mails, Premiere-Ankündigung 1. Advent | E6: „Noch X Tage“, Blick hinter Türchen 1, Gewinnspiel-Aufruf zum 1. Advent | F6: Aufrufe, Anmeldungen | G6: 0 € (organisch)
A7: 6 Kalenderphase | B7: 1.12.–24.12. | C7: Käufer halten, Nachkäufer gewinnen | D7: Tägliche Posts, Sonntags-Lives, Mails, Retargeting ❓ | E7: Täglicher Türchen-Teaser (ohne alles zu verraten), Wochen-Gewinnspiele, 20.12. CD-Rabatt, 24.12. Finale | F7: Käufe pro Woche, Teilnehmer an Gewinnspielen | G7: z. B. 100–200 € ❓
A8: 7 Nachbereitung | B8: 25.12.–31.12. | C8: Dank, Kunden binden, 2027 vorbereiten | D8: Mail, Instagram, YouTube | E8: Dank, Gewinner zeigen, Konzerte 2027 | F8: Neue Abonnenten, Newsletter-Öffnungen | G8: 0 €
A10: Hinweis: Alle Budgets, Messgrößen und bezahlten Kanäle sind Vorschläge von Claude (❓) und wurden von Jannik noch nicht entschieden. Quelle der organischen Idee „tägliche Clips“: Notion-Plan vom 6.10.2026.

Sheet Offene Fragen
A1: Nr | B1: Frage | C1: Wer antwortet | D1: Wird gebraucht bis | E1: Status | F1: Antwort (Jannik, 24.10.)
A2: 1 | B2: Wer macht was im Team, wie viele Stunden pro Woche? | C2: Jannik + Eltern | D2: 46321 | E2: beantwortet | F2: Jannik 20 Std./Woche: Social Media, Warteliste, Website/Shop, Konzerte, Videoschnitt. Mutter: Videodreh. Vater: vor der Kamera. Eltern zusammen ca. 10 Std./Woche.
A3: 2 | B3: Gesamtbudget und Werbebudget? | C3: Jannik + Eltern | D3: 46322 | E3: offen | F3: Jannik fragt nach.
A4: 3 | B4: Welche Lieder (alle) sind im Kalender, welches Playback ist eigen oder fremd? | C4: Jannik + David | D4: 46322 | E4: offen | F4: Jannik fragt nach (Playback eigen oder fremd).
A5: 4 | B5: Dreh-Termine von David (Blöcke A–E)? | C5: Jannik + David | D5: 46321 | E5: offen | F5: Noch keine Termine.
A6: 5 | B6: Zugang: Plugin oder eigener Server, wer baut es, Admin-Zugang? | C6: Jannik | D6: 46321 | E6: offen
A7: 6 | B7: Zahlarten außer PayPal, Verkauf weltweit? | C7: Jannik | D7: 46322 | E7: beantwortet | F7: PayPal und alles, was der Shop liefert.
A8: 7 | B8: Link oder Text der aktuellen Warteliste-Seite? | C8: Jannik | D8: 46320 | E8: offen | F8: Jannik fragt an und schickt es.
A9: 8 | B9: Text der Konzertseite 2027 (Homepage)? | C9: Jannik | D9: 46320 | E9: offen | F9: Auf der Homepage. Claude hat in dieser Sitzung keinen Browser, Jannik kopiert den Text.
A10: 9 | B10: Absender-Name und -Adresse in Brevo? | C10: Jannik | D10: 46321 | E10: offen | F10: Jannik nennt ihn später.
A11: 10 | B11: Welche Teaser-Ausschnitte dürfen öffentlich werden? | C11: Jannik | D11: 46322 | E11: offen | F11: Jannik sagt später, welche.
A12: 11 | B12: Welche Videos bekommen eine englische und koreanische Fassung? | C12: Jannik | D12: 46323 | E12: beantwortet | F12: Alle, die keine Musik sind (Geschichten u. ä.).
A13: 12 | B13: Wann bis wann zählt ein Kauf für die jeweilige Ziehung (z. B. bis Ziehungstag 12 Uhr)? | C13: Jannik | D13: 46327 | E13: beantwortet | F13: Kauf zählt ab Verkaufsstart bis zum Beginn der jeweiligen Ziehung (Claude-Auslegung, bitte bestätigen).
A14: 13 | B14: Live-Plattform (YouTube/TikTok) und Uhrzeit (12 oder 14 Uhr DE)? | C14: Jannik + David | D14: 46334 | E14: beantwortet | F14: YouTube, 14 Uhr deutsche Zeit.
A15: 14 | B15: Mindestalter und Länderliste für das Gewinnspiel? | C15: Jannik + Kanzlei | D15: 46327 | E15: beantwortet | F15: 18. Länder: Deutschland, Niederlande, Tschechien, Frankreich, Schweiz, Österreich, Luxemburg, Belgien, Südkorea, USA, Paraguay.
A16: 15 | B16: Türchen 24: Breite und Höhe dreifach oder Fläche dreifach? | C16: Jannik | D16: 46327 | E16: beantwortet | F16: Breite dreifach, Höhe gleich wie die anderen Türchen (Jannik, 24.10.).
A17: 16 | B17: Videoformat des Kalenders: 16:9? | C17: Jannik | D17: 46321 | E17: beantwortet | F17: 16:9.
A18: 17 | B18: Welche Werbekanäle bezahlt (Meta, YouTube) und welches Budget? | C18: Jannik + Eltern | D18: 46322 | E18: offen | F18: Kanäle und Budget müssen noch festgelegt werden.
A19: 18 | B19: Wer schneidet die Videos (Jannik, Videoagent, extern)? | C19: Jannik | D19: 46321 | E19: beantwortet | F19: Jannik und Videoagent.
